lib/__init__.py
lib/channels.py
lib/errors.py
lib/examples.py
lib/groups.py
lib/messages.py
lib/response.py
lib/sdk.py
lib/things.py
lib/users.py
tests/__init__.py
tests/test_channels.py
tests/test_groups.py
tests/test_messages.py
tests/test_things.py
tests/test_users.py
tests/test_version.py
Mainflux-0.0.1.dist-info/METADATA
Mainflux-0.0.1.dist-info/WHEEL
Mainflux-0.0.1.dist-info/top_level.txt
Mainflux-0.0.1.dist-info/RECORD
