Metadata-Version: 2.1
Name: Mainflux
Version: 0.0.1
Summary: Python SDK
Home-page: https://github.com/mainflux/sdk-py
Author: Filip Bugarski
Author-email: filipbugarski@gmail.com
License: UNKNOWN
Project-URL: Bug Tracker, https://github.com/mainflux/sdk-py
Platform: UNKNOWN
Classifier: Programming Language :: Python :: 3.8
Classifier: Operating System :: OS Independent
Requires-Python: >=3.6
